area_mehak/__init__.py
area_mehak/shapes.py
area_lib_mehak-0.1.2.dist-info/METADATA
area_lib_mehak-0.1.2.dist-info/WHEEL
area_lib_mehak-0.1.2.dist-info/top_level.txt
area_lib_mehak-0.1.2.dist-info/RECORD
