Metadata-Version: 2.4
Name: area-lib-mehak
Version: 0.1.2
Summary: A simple library to calculate areas of shapes like circle, triangle, square
Author: Mehak
License: MIT
